inventree_shopify/ShopifyPlugin.py
inventree_shopify/__init__.py
inventree_shopify/admin.py
inventree_shopify/models.py
inventree_shopify/migrations/0001_initial.py
inventree_shopify/migrations/__init__.py
inventree_shopify/templates/shopify/increase.html
inventree_shopify/templates/shopify/index.html
inventree_shopify/templates/shopify/webhooks.html
inventree_shopify-1.1.0.dist-info/LICENSE
inventree_shopify-1.1.0.dist-info/METADATA
inventree_shopify-1.1.0.dist-info/WHEEL
inventree_shopify-1.1.0.dist-info/entry_points.txt
inventree_shopify-1.1.0.dist-info/top_level.txt
inventree_shopify-1.1.0.dist-info/RECORD
