Metadata-Version: 2.1
Name: inventree-shopify
Version: 1.1.0
Summary: Shopify integration for InvenTree
Author-email: Matthias Mair <code@mjmair.com>
License: MIT
Project-URL: Repository, https://github.com/invenhost/inventree-shopify
Project-URL: Bug Tracker, https://github.com/invenhost/inventree-shopify/issues
Keywords: inventree,inventree-plugin,shopify
Classifier: Programming Language :: Python :: 3
Classifier: Operating System :: OS Independent
Classifier: Development Status :: 5 - Production/Stable
Classifier: Environment :: Plugins
Classifier: Framework :: Django
Classifier: Intended Audience :: Developers
Classifier: Intended Audience :: Manufacturing
Classifier: Intended Audience :: End Users/Desktop
Classifier: Topic :: Scientific/Engineering
Requires-Python: >=3.9
License-File: LICENSE
Requires-Dist: requests
Requires-Dist: django
Provides-Extra: dev
Requires-Dist: twine ; extra == 'dev'
Requires-Dist: setuptools ; extra == 'dev'
